setup.py
roundtm/__init__.py
roundtm/__main__.py
roundtm/console.py
roundtm/events.py
roundtm/generators.py
roundtm/objects.py
roundtm/stats.py
roundtm.egg-info/PKG-INFO
roundtm.egg-info/SOURCES.txt
roundtm.egg-info/dependency_links.txt
roundtm.egg-info/entry_points.txt
roundtm.egg-info/requires.txt
roundtm.egg-info/top_level.txt
roundtm/test/__init__.py