Metadata-Version: 1.1
Name: roundtm
Version: 0.1
Summary: RoundTM - A Round based Tournament Manager.
Home-page: https://github.com/Toilal/roundtm
Author: Rémi Alvergnat
Author-email: toilal.dev@gmail.com
License: LGPLv3
Keywords: round based tournament manager play players sport game
Platform: UNKNOWN
Classifier: Development Status :: 2 - Pre-Alpha
Classifier: License :: OSI Approved :: GNU Lesser General Public License v3 (LGPLv3)
Classifier: Operating System :: OS Independent
Classifier: Intended Audience :: End Users/Desktop
Classifier: Programming Language :: Python :: 2
Classifier: Programming Language :: Python :: 3
Classifier: Topic :: Games/Entertainment
